alg_lomv.cpython-39-darwin.so
ffp_minvar.cpython-39-darwin.so
alg_lomv/so.cpython-39-darwin.so
ffp_minvar/__init__.py
ffp_minvar/alg_lomv.cpython-39-darwin.so
ffp_minvar/ffp_minvar_lib.py
ffp_minvar/shared.cpython-39-darwin.so
ffp_minvar/Contents/Resources/DWARF/alg_lomv.so
ffp_minvar/alg_lomv/so.cpython-39-darwin.so
ffp_minvar/include/alg_lomv.h
ffp_minvar/src/alg_lomv.c
shared/alg_lomv/so.cpython-39-darwin.so
ffp_minvar-0.1.30.dist-info/LICENSE
ffp_minvar-0.1.30.dist-info/METADATA
ffp_minvar-0.1.30.dist-info/WHEEL
ffp_minvar-0.1.30.dist-info/top_level.txt
ffp_minvar-0.1.30.dist-info/RECORD
