Metadata-Version: 2.1
Name: ffp-minvar
Version: 0.1.30
Summary: rewritten python package of ffp_minvar algorithm
Home-page: https://github.com/luciusluo/ffp_minvar
Author: Lucius Luo
Author-email: lucius0228@gmail.com
License: UNKNOWN
Project-URL: Bug Tracker, https://github.com/luciusluo/ffp_minvar/issues
Platform: UNKNOWN
Classifier: Programming Language :: Python :: 3
Classifier: License :: OSI Approved :: MIT License
Classifier: Operating System :: OS Independent
Requires-Python: >=3.6
License-File: LICENSE
